idris_python/__init__.py
idris_python/abstract_machine.py
idris_python/cli.py
idris_python/idris_apis.py
idris_python/loader.py
idris_python/read_ir.py
idris_python/runtime.py
idris_python-0.25.dist-info/METADATA
idris_python-0.25.dist-info/RECORD
idris_python-0.25.dist-info/WHEEL
idris_python-0.25.dist-info/entry_points.txt
idris_python-0.25.dist-info/top_level.txt
