Metadata-Version: 2.1
Name: idris-python
Version: 0.25
Summary: Loader for a kind of Idris IR.
Home-page: https://github.com/thautwarm/idris-python
Author: thautwarm
Author-email: twshere@outlook.com
License: bsd3
Keywords: Idris,Dependent Types,Type Safety,Compiler
Platform: any
Classifier: Programming Language :: Python :: 3.5
Classifier: Programming Language :: Python :: 3.6
Classifier: Programming Language :: Python :: 3.7
Classifier: Programming Language :: Python :: Implementation :: CPython
Requires-Dist: wisepy2
Requires-Dist: toml
